daogao/__init__.py
daogao/server.py
daogao-0.1.1.dist-info/DESCRIPTION.rst
daogao-0.1.1.dist-info/METADATA
daogao-0.1.1.dist-info/RECORD
daogao-0.1.1.dist-info/WHEEL
daogao-0.1.1.dist-info/metadata.json
daogao-0.1.1.dist-info/top_level.txt
