Metadata-Version: 2.0
Name: daogao
Version: 0.1.1
Summary: Excel generation daemon.
Home-page: https://bitbucket.org/gamikun/daogao
Author: Gamaliel Espinoza Macedo
Author-email: gamaliel.espinoza@gmail.com
License: UNKNOWN
Platform: UNKNOWN
Classifier: Development Status :: 4 - Beta
Classifier: Intended Audience :: Developers
Classifier: Natural Language :: English
Classifier: Programming Language :: Python :: 2.7
Requires-Dist: openpyxl
Requires-Dist: pillow
Requires-Dist: psycopg2
Requires-Dist: requests
Requires-Dist: tornado
